lib_version_remla24_team02/__init__.py
lib_version_remla24_team02/version_util.py
lib_version_remla24_team02-0.0.5.dist-info/LICENSE
lib_version_remla24_team02-0.0.5.dist-info/METADATA
lib_version_remla24_team02-0.0.5.dist-info/WHEEL
lib_version_remla24_team02-0.0.5.dist-info/top_level.txt
lib_version_remla24_team02-0.0.5.dist-info/RECORD
